[{"Name":"Troy","Surname":"Beer","Email":"Viviane.Raynor72@yahoo.com","DateOfBirth":"1957-12-17T06:11:21.8026283+04:00"},{"Name":"Becky","Surname":"Little","Email":"Everardo.Doyle78@gmail.com","DateOfBirth":"1982-12-05T18:51:24.1538202+04:00"},{"Name":"Glenn","Surname":"Gutkowski","Email":"Johathan_Flatley@gmail.com","DateOfBirth":"1991-02-02T17:19:10.5964267+04:00"},{"Name":"Troy","Surname":"Okuneva","Email":"Clara_Bradtke@gmail.com","DateOfBirth":"1965-04-26T13:47:13.6547398+05:00"},{"Name":"Kenneth","Surname":"Oberbrunner","Email":"Pablo.Rempel50@gmail.com","DateOfBirth":"1981-05-12T01:30:40.8349275+05:00"},{"Name":"Frankie","Surname":"Mayer","Email":"Hertha_Trantow83@hotmail.com","DateOfBirth":"1999-06-16T03:51:10.3098598+05:00"},{"Name":"Floyd","Surname":"Hamill","Email":"Forrest33@hotmail.com","DateOfBirth":"1996-10-03T23:00:55.1806051+05:00"},{"Name":"Sue","Surname":"Kautzer","Email":"Leopoldo_Bosco@gmail.com","DateOfBirth":"1964-07-04T09:24:47.2491144+05:00"},{"Name":"Jan","Surname":"Toy","Email":"Viva62@gmail.com","DateOfBirth":"1985-09-04T11:37:29.8438974+05:00"},{"Name":"Peter","Surname":"Graham","Email":"Adonis_Leffler@yahoo.com","DateOfBirth":"1993-01-21T03:42:00.97137+04:00"},{"Name":"Wilma","Surname":"Jaskolski","Email":"Luisa_Koch@hotmail.com","DateOfBirth":"1960-09-19T18:42:48.9874504+05:00"},{"Name":"Benny","Surname":"Lueilwitz","Email":"Carolina.Skiles33@hotmail.com","DateOfBirth":"2004-01-18T23:15:47.2305117+04:00"},{"Name":"Brian","Surname":"Renner","Email":"Dariana.Swift73@gmail.com","DateOfBirth":"1979-04-09T02:05:58.9256557+05:00"},{"Name":"Maryann","Surname":"Boehm","Email":"Bennett.Turcotte@yahoo.com","DateOfBirth":"1961-02-05T11:09:12.4075696+04:00"},{"Name":"Willie","Surname":"Harvey","Email":"Kelly60@yahoo.com","DateOfBirth":"1968-04-09T23:27:52.9267436+05:00"},{"Name":"Bethany","Surname":"Cassin","Email":"Alanna.Toy56@yahoo.com","DateOfBirth":"1962-06-22T00:40:59.7137793+05:00"},{"Name":"Wilbert","Surname":"Williamson","Email":"Diamond.Harris79@hotmail.com","DateOfBirth":"1970-01-19T06:45:51.4404512+04:00"},{"Name":"Alison","Surname":"Lehner","Email":"Lola34@gmail.com","DateOfBirth":"1971-09-29T19:08:32.8488136+05:00"},{"Name":"Phillip","Surname":"Stiedemann","Email":"Antonio_Paucek@hotmail.com","DateOfBirth":"1997-05-18T23:22:03.5038245+05:00"},{"Name":"Antoinette","Surname":"Fisher","Email":"Ashlee61@hotmail.com","DateOfBirth":"1995-09-30T23:50:55.788995+05:00"},{"Name":"Hilda","Surname":"Adams","Email":"Kenneth_Little82@hotmail.com","DateOfBirth":"1956-10-02T19:47:20.4803638+05:00"},{"Name":"Gina","Surname":"Runte","Email":"Rosemary_Simonis18@yahoo.com","DateOfBirth":"1967-09-03T06:54:48.3852646+05:00"},{"Name":"Stacy","Surname":"DuBuque","Email":"Melyssa_Wiza@gmail.com","DateOfBirth":"1969-10-27T12:41:32.8315429+04:00"},{"Name":"Lydia","Surname":"Armstrong","Email":"Gina16@gmail.com","DateOfBirth":"1987-12-08T10:19:40.1282028+04:00"},{"Name":"Manuel","Surname":"Daugherty","Email":"Cleora15@hotmail.com","DateOfBirth":"1987-06-11T00:34:03.8353549+05:00"},{"Name":"Ross","Surname":"Conn","Email":"Nya26@gmail.com","DateOfBirth":"1992-07-26T18:36:00.0940081+05:00"},{"Name":"Beatrice","Surname":"Grady","Email":"Geoffrey.Rowe70@hotmail.com","DateOfBirth":"1985-10-25T09:57:52.7098367+05:00"},{"Name":"Lindsay","Surname":"Gutkowski","Email":"Alexandria87@yahoo.com","DateOfBirth":"1978-09-27T06:58:59.9620071+05:00"},{"Name":"Mandy","Surname":"King","Email":"Ardella41@gmail.com","DateOfBirth":"1993-01-10T15:59:32.6009035+04:00"},{"Name":"Spencer","Surname":"Schoen","Email":"Morgan26@yahoo.com","DateOfBirth":"1991-02-25T17:27:20.89022+04:00"},{"Name":"Cesar","Surname":"Smith","Email":"Houston4@hotmail.com","DateOfBirth":"1973-12-23T05:03:16.5709565+04:00"},{"Name":"Dora","Surname":"Pfeffer","Email":"Letitia91@gmail.com","DateOfBirth":"2002-08-12T23:33:11.8158792+05:00"},{"Name":"Cesar","Surname":"Mayert","Email":"Abbey28@yahoo.com","DateOfBirth":"1988-06-12T21:28:58.2670502+05:00"},{"Name":"Hannah","Surname":"Reynolds","Email":"Judd.Hodkiewicz89@hotmail.com","DateOfBirth":"1999-06-20T13:04:04.2968644+05:00"},{"Name":"Delores","Surname":"Dietrich","Email":"Cali.Ebert15@gmail.com","DateOfBirth":"1954-11-30T14:37:02.3442751+04:00"},{"Name":"Ruth","Surname":"Schamberger","Email":"Lea.Parker@hotmail.com","DateOfBirth":"1999-02-12T11:15:49.3857678+04:00"},{"Name":"Carrie","Surname":"Wisozk","Email":"Garett98@gmail.com","DateOfBirth":"1963-11-15T03:53:47.2245196+04:00"},{"Name":"Muriel","Surname":"Koss","Email":"Vena55@hotmail.com","DateOfBirth":"1963-10-27T12:21:43.2895303+04:00"},{"Name":"Myron","Surname":"Erdman","Email":"Jacquelyn_Funk@hotmail.com","DateOfBirth":"1976-12-07T12:45:38.2269924+04:00"},{"Name":"Hannah","Surname":"Hyatt","Email":"Carson32@hotmail.com","DateOfBirth":"1977-08-18T06:27:44.1599724+05:00"},{"Name":"Jeremiah","Surname":"Kemmer","Email":"Davon84@hotmail.com","DateOfBirth":"1989-04-29T05:04:34.9813376+05:00"},{"Name":"Barbara","Surname":"Pfeffer","Email":"Ernesto_Carroll@gmail.com","DateOfBirth":"1967-08-28T10:40:11.7139685+05:00"},{"Name":"Darren","Surname":"Windler","Email":"Emery.White64@yahoo.com","DateOfBirth":"1978-04-20T01:43:21.1394321+05:00"},{"Name":"George","Surname":"Swaniawski","Email":"Trace.Volkman@yahoo.com","DateOfBirth":"2001-04-01T17:46:19.5029115+05:00"},{"Name":"Sherri","Surname":"Hayes","Email":"Stanford_Gleichner@yahoo.com","DateOfBirth":"1980-11-17T03:28:07.94779+04:00"},{"Name":"Lillie","Surname":"Legros","Email":"Sim.Bashirian61@hotmail.com","DateOfBirth":"1990-01-08T00:01:54.6752672+04:00"},{"Name":"Freda","Surname":"Schroeder","Email":"Adriel.Kling45@hotmail.com","DateOfBirth":"1985-05-14T05:53:49.5292861+05:00"},{"Name":"Morris","Surname":"Macejkovic","Email":"Jovan83@hotmail.com","DateOfBirth":"1992-10-25T05:18:37.5867508+04:00"},{"Name":"Tonya","Surname":"Bechtelar","Email":"Serena_Runolfsdottir@yahoo.com","DateOfBirth":"2001-11-23T15:19:14.396828+04:00"},{"Name":"Matthew","Surname":"Renner","Email":"Cheyanne_Wuckert80@yahoo.com","DateOfBirth":"1993-04-27T15:54:14.2439911+05:00"}]